README
setup.py
src/SpiffIntegrator/Api.py
src/SpiffIntegrator/Exception.py
src/SpiffIntegrator/Package.py
src/SpiffIntegrator/PackageDB.py
src/SpiffIntegrator/PackageManager.py
src/SpiffIntegrator/Parser.py
src/SpiffIntegrator/__init__.py
src/SpiffIntegrator/functions.py
src/SpiffIntegrator.egg-info/PKG-INFO
src/SpiffIntegrator.egg-info/SOURCES.txt
src/SpiffIntegrator.egg-info/dependency_links.txt
src/SpiffIntegrator.egg-info/top_level.txt