Metadata-Version: 1.1
Name: SpiffIntegrator
Version: 0.2.0
Summary: A package/plugin manager implemented in Python
Home-page: http://code.google.com/p/spiff-integrator/
Author: Samuel Abels
Author-email: cheeseshop.python.org@debain.org
License: GPLv2
Keywords: spiff integrator package manager dpkg install uninstall dependency
Platform: UNKNOWN
Classifier: Development Status :: 5 - Production/Stable
Classifier: Intended Audience :: Developers
Classifier: License :: OSI Approved :: GNU General Public License (GPL)
Classifier: Programming Language :: Python
Classifier: Topic :: Software Development :: Libraries
Classifier: Topic :: Software Development :: Libraries :: Python Modules
Requires: sqlalchemy
